{"ghosteye_initapi.md":"637a0ff3","leetcode_index.md":"b2b2b7a5","leetcode_387.md":"4bf15b0f","leetcode_45.md":"7f6cdbaf","leetcode_59.md":"ba680e41","leetcode_66.md":"396bafec","leetcode_70.md":"b6eb37bd","other_docker.md":"64581975","other_python.md":"599984e4","other_error.md":"537580d1","leetcode_20.md":"bd794347","other_books.md":"ec7ed315","leetcode_219.md":"bc1aa7d5","other_rn_flutter_weex.md":"b10aabc4","leetcode_14.md":"c7f87931","leetcode_27.md":"c1838098","handbook_coding-specification.md":"4e595c28","other_index.md":"b7959f8e","other_install.md":"999fd03d","other_js.md":"b204254e","other_mini.md":"49019c37","other_miniprogram.md":"9505f5d8","other_quotations.md":"97cbe1ec","other_test.md":"60102795","other_vscode.md":"55b8dd88","目标.md":"c5de215d","ghosteye_create-xm.md":"02860231","demo_index.md":"430a54a4","demo_stars.md":"505c25d8","demo_solar.md":"54967520","demo_virtual-list.md":"bc4e8de4","handbook_index.md":"dffd5fa8","handbook_mpvue.md":"aa0b8936","handbook_node.md":"627358a4","handbook_other.md":"241d5a2c","handbook_git.md":"737a150e","interview_engineering.md":"da6bc031","interview_prepare.md":"f52afd42","leetcode_03.md":"5768c3c0","leetcode_09.md":"2f6bc86c","index.md":"74ed6d5c","leetcode_07.md":"edfbead1","leetcode_121.md":"af10acf0","leetcode_01.md":"d7daf579","interview_index.md":"fb0939e8","leetcode_242.md":"807cb4b7","handbook_npm.md":"628b0926","handbook_settings.md":"0b22c579","handbook_vue.md":"8010128c","handbook_webpack.md":"c632d72c","leetcode_36.md":"c11f7016","leetcode_125.md":"ce0e568f","handbook_javascript.md":"145948d5","handbook_css.md":"57cff04a"}
